pypinyin/__init__.py
pypinyin/__init__.pyi
pypinyin/__main__.py
pypinyin/compat.py
pypinyin/compat.pyi
pypinyin/constants.py
pypinyin/constants.pyi
pypinyin/converter.py
pypinyin/converter.pyi
pypinyin/core.py
pypinyin/core.pyi
pypinyin/phonetic_symbol.py
pypinyin/phonetic_symbol.pyi
pypinyin/phrases_dict.json
pypinyin/phrases_dict.py
pypinyin/phrases_dict.pyi
pypinyin/pinyin_dict.json
pypinyin/pinyin_dict.py
pypinyin/pinyin_dict.pyi
pypinyin/py.typed
pypinyin/runner.py
pypinyin/runner.pyi
pypinyin/standard.py
pypinyin/standard.pyi
pypinyin/utils.py
pypinyin/utils.pyi
pypinyin/__pyinstaller/__init__.py
pypinyin/__pyinstaller/__init__.pyi
pypinyin/__pyinstaller/hook-pypinyin.py
pypinyin/contrib/__init__.py
pypinyin/contrib/_tone_rule.py
pypinyin/contrib/_tone_rule.pyi
pypinyin/contrib/mmseg.py
pypinyin/contrib/mmseg.pyi
pypinyin/contrib/neutral_tone.py
pypinyin/contrib/neutral_tone.pyi
pypinyin/contrib/tone_convert.py
pypinyin/contrib/tone_convert.pyi
pypinyin/contrib/tone_sandhi.py
pypinyin/contrib/tone_sandhi.pyi
pypinyin/contrib/uv.py
pypinyin/contrib/uv.pyi
pypinyin/seg/__init__.py
pypinyin/seg/mmseg.py
pypinyin/seg/mmseg.pyi
pypinyin/seg/simpleseg.py
pypinyin/seg/simpleseg.pyi
pypinyin/style/__init__.py
pypinyin/style/__init__.pyi
pypinyin/style/_constants.py
pypinyin/style/_constants.pyi
pypinyin/style/_tone_convert.py
pypinyin/style/_tone_convert.pyi
pypinyin/style/_tone_rule.py
pypinyin/style/_tone_rule.pyi
pypinyin/style/_utils.py
pypinyin/style/_utils.pyi
pypinyin/style/bopomofo.py
pypinyin/style/bopomofo.pyi
pypinyin/style/cyrillic.py
pypinyin/style/cyrillic.pyi
pypinyin/style/finals.py
pypinyin/style/finals.pyi
pypinyin/style/initials.py
pypinyin/style/initials.pyi
pypinyin/style/others.py
pypinyin/style/others.pyi
pypinyin/style/tone.py
pypinyin/style/tone.pyi
pypinyin/style/wadegiles.py
pypinyin/style/wadegiles.pyi
pypinyin/tools/__init__.py
pypinyin/tools/toneconvert.py
pypinyin/tools/toneconvert.pyi
pypinyin-0.53.0.dist-info/LICENSE.txt
pypinyin-0.53.0.dist-info/METADATA
pypinyin-0.53.0.dist-info/WHEEL
pypinyin-0.53.0.dist-info/entry_points.txt
pypinyin-0.53.0.dist-info/top_level.txt
pypinyin-0.53.0.dist-info/RECORD
