Metadata-Version: 2.1
Name: pypinyin
Version: 0.53.0
Summary: 汉字拼音转换模块/工具.
Home-page: https://github.com/mozillazg/python-pinyin
Author: mozillazg, 闲耘
Author-email: mozillazg101@gmail.com
License: MIT
Project-URL: Documentation, https://pypinyin.readthedocs.io/
Project-URL: Source, https://github.com/mozillazg/python-pinyin
Project-URL: Tracker, https://github.com/mozillazg/python-pinyin/issues
Keywords: pinyin,拼音
Platform: UNKNOWN
Classifier: Development Status :: 5 - Production/Stable
Classifier: Intended Audience :: Developers
Classifier: License :: OSI Approved :: MIT License
Classifier: Operating System :: OS Independent
Classifier: Programming Language :: Python
Classifier: Programming Language :: Python :: 2
Classifier: Programming Language :: Python :: 2.7
Classifier: Programming Language :: Python :: 3
Classifier: Programming Language :: Python :: 3.4
Classifier: Programming Language :: Python :: 3.5
Classifier: Programming Language :: Python :: 3.6
Classifier: Programming Language :: Python :: 3.7
Classifier: Programming Language :: Python :: 3.8
Classifier: Programming Language :: Python :: 3.9
Classifier: Programming Language :: Python :: 3.10
Classifier: Programming Language :: Python :: 3.11
Classifier: Programming Language :: Python :: 3.12
Classifier: Programming Language :: Python :: Implementation :: CPython
Classifier: Programming Language :: Python :: Implementation :: PyPy
Classifier: Topic :: Utilities
Classifier: Topic :: Text Processing
Requires-Python: >=2.6, !=3.0.*, !=3.1.*, !=3.2.*, <4
License-File: LICENSE.txt
